probmetrics/__about__.py
probmetrics/__init__.py
probmetrics/calibrators.py
probmetrics/distributions.py
probmetrics/metrics.py
probmetrics/splitters.py
probmetrics/torch_utils.py
probmetrics/utils.py
probmetrics/saga/__init__.py
probmetrics/saga/binary.py
probmetrics/saga/matrix_scaling.py
probmetrics/saga/utils.py
probmetrics/saga/vector_scaling.py
probmetrics-1.1.0.dist-info/METADATA
probmetrics-1.1.0.dist-info/WHEEL
probmetrics-1.1.0.dist-info/licenses/LICENSE.txt
probmetrics-1.1.0.dist-info/RECORD
