Metadata-Version: 2.4
Name: probmetrics
Version: 1.1.0
Summary: Probabilistic metrics and calibration methods
Project-URL: Documentation, https://github.com/dholzmueller/probmetrics#readme
Project-URL: Issues, https://github.com/dholzmueller/probmetrics/issues
Project-URL: Source, https://github.com/dholzmueller/probmetrics
Author: David Holzmüller
License-Expression: Apache-2.0
License-File: LICENSE.txt
Keywords: Calibration,Classification,Metrics,Refinement
Classifier: Development Status :: 4 - Beta
Classifier: License :: OSI Approved :: Apache Software License
Classifier: Programming Language :: Python
Classifier: Programming Language :: Python :: 3.9
Classifier: Programming Language :: Python :: 3.10
Classifier: Programming Language :: Python :: 3.11
Classifier: Programming Language :: Python :: 3.12
Classifier: Programming Language :: Python :: Implementation :: CPython
Classifier: Programming Language :: Python :: Implementation :: PyPy
Requires-Python: >=3.9
Requires-Dist: numba
Requires-Dist: numpy>=1.25
Requires-Dist: scikit-learn>=1.3
Requires-Dist: torch>=2.0
Requires-Dist: torchmetrics>=1.2.1
Provides-Extra: dev
Requires-Dist: fire; extra == 'dev'
Requires-Dist: matplotlib>=3.0; extra == 'dev'
Requires-Dist: myst-parser>=3.0; extra == 'dev'
Requires-Dist: pytest-cov>=4.0; extra == 'dev'
Requires-Dist: pytest>=7.0; extra == 'dev'
Requires-Dist: scipy; extra == 'dev'
Requires-Dist: sphinx-rtd-theme>=2.0; extra == 'dev'
Requires-Dist: sphinx>=7.0; extra == 'dev'
Provides-Extra: dirichletcal
Requires-Dist: dirichletcal; extra == 'dirichletcal'
Provides-Extra: extra
Requires-Dist: cir-model; extra == 'extra'
Requires-Dist: netcal; extra == 'extra'
Requires-Dist: pytorch-minimize; extra == 'extra'
Requires-Dist: relplot; extra == 'extra'
Requires-Dist: scikit-learn<1.7,>=1.3; extra == 'extra'
Requires-Dist: venn-abers; extra == 'extra'
